torchling/__init__.py
torchling/tensor.py
torchling/layers/__init__.py
torchling/layers/layers.py
torchling/losses/__init__.py
torchling/losses/losses.py
torchling/models/__init__.py
torchling/models/models.py
torchling/optimisers/__init__.py
torchling/optimisers/optimisers.py
torchling-1.0.0.dist-info/licenses/LICENSE
torchling-1.0.0.dist-info/METADATA
torchling-1.0.0.dist-info/WHEEL
torchling-1.0.0.dist-info/top_level.txt
torchling-1.0.0.dist-info/RECORD
