Metadata-Version: 2.4
Name: torchling
Version: 1.0.0
Summary: A minimal deep learning library using numpy.
Author-email: Piotr Brutkowski <piotrbrutkowski@yahoo.com>
License: MIT License
Project-URL: Homepage, https://github.com/pbrut/torchling
Project-URL: Repository, https://github.com/pbrut/torchling
Classifier: Programming Language :: Python :: 3
Classifier: License :: OSI Approved :: MIT License
Classifier: Operating System :: OS Independent
Classifier: Intended Audience :: Developers
Classifier: Topic :: Scientific/Engineering :: Artificial Intelligence
Requires-Python: >=3.8
License-File: LICENSE
Requires-Dist: numpy>=1.26.4
Dynamic: license-file
